gppy/__init__.py
gppy/gtf.py
gppy-0.1.4.dist-info/LICENSE
gppy-0.1.4.dist-info/METADATA
gppy-0.1.4.dist-info/WHEEL
gppy-0.1.4.dist-info/entry_points.txt
gppy-0.1.4.dist-info/top_level.txt
gppy-0.1.4.dist-info/RECORD
