Metadata-Version: 2.1
Name: gppy
Version: 0.1.4
Summary: Genomic Position with Python (GPPY)
Home-page: https://github.com/mt1022/gppy
Author: Hong Zhang (mt1022)
Author-email: gxelab@163.com
Project-URL: Bug Tracker, https://github.com/mt1022/gppy/issues
Classifier: Programming Language :: Python :: 3
Classifier: License :: OSI Approved :: MIT License
Classifier: Operating System :: OS Independent
Classifier: Intended Audience :: Science/Research
Classifier: Topic :: Scientific/Engineering :: Bio-Informatics
Requires-Python: >=3.9
License-File: LICENSE
